[
  {
    "route": "200Moskalenki",
    "index": 1,
    "title": "\"Москаленки\"",
    "startDate": "24.04.2021",
    "startTime": "8.00",
    "totalTime": 13.5,
    "distance": 200,
    "description": "10 лет веломарафонскому клубу \"Цепная Реакция\"!"
  },
  {
    "route": "200Serebryanoye",
    "index": 1,
    "title": "\"Серебряное\"",
    "startDate": "09.05.2021",
    "startTime": "7.00",
    "totalTime": 13.5,
    "distance": 200,
    "description": ""
  },
  {
    "route": "300Cherlak",
    "index": 1,
    "title": "\"Черлак\"",
    "startDate": "15.05.2021",
    "startTime": "7.00",
    "totalTime": 20,
    "distance": 300,
    "description": ""
  },
  {
    "route": "400Bolsherechye",
    "index": 1,
    "title": "\"Большеречье\"",
    "startDate": "29.05.2021",
    "startTime": "7.00",
    "totalTime": 27,
    "distance": 400,
    "description": ""
  },
  {
    "route": "600CherlakIsilkul",
    "index": 1,
    "title": "\"Черлак - Исилькуль\"",
    "startDate": "12.06.2021",
    "startTime": "7.00",
    "totalTime": 40,
    "distance": 600,
    "description": ""
  },
  {
    "route": "200Novouralsky",
    "index": 1,
    "title": "\"Новоуральский\"",
    "startDate": "26.06.2021",
    "startTime": "7.00",
    "totalTime": 13.5,
    "distance": 200,
    "description": ""
  },
  {
    "route": "300TavricheskoeSargatskoe",
    "index": 1,
    "title": "\"Таврическое - Саргатское\"",
    "startDate": "10.07.2021",
    "startTime": "7.00",
    "totalTime": 20,
    "distance": 300,
    "description": ""
  },
  {
    "route": "400MoskalenkiIrtysh",
    "index": 1,
    "title": "\"Москаленки - Иртыш\"",
    "startDate": "24.07.2021",
    "startTime": "7.00",
    "totalTime": 27,
    "distance": 400,
    "description": ""
  },
  {
    "route": "600CherlakIsilkul",
    "index": 2,
    "title": "\"Черлак - Исилькуль\"",
    "startDate": "07.08.2021",
    "startTime": "8.00",
    "totalTime": 40,
    "distance": 600,
    "description": ""
  },
  {
    "route": "200Pavlogradka",
    "index": 1,
    "title": "\"Павлоградка\"",
    "startDate": "14.08.2021",
    "startTime": "7.00",
    "totalTime": 13.5,
    "distance": 200,
    "description": ""
  },
  {
    "route": "300Isilkul",
    "index": 1,
    "title": "\"Исилькуль\"",
    "startDate": "28.08.2021",
    "startTime": "7.00",
    "totalTime": 20,
    "distance": 300,
    "description": ""
  },
  {
    "route": "200Irtysh",
    "index": 1,
    "title": "\"Иртыш\"",
    "startDate": "11.09.2021",
    "startTime": "8.00",
    "totalTime": 13.5,
    "distance": 200,
    "description": "100 лет мировому рандоннёрскому движению!"
  }
]
